run_SnapHiC_D.py
SnapHiC_D/SnapHiC_D.py
SnapHiC_D/__init__.py
SnapHiC_D/__main__.py
SnapHiC_D-0.1.0.dist-info/LICENSE
SnapHiC_D-0.1.0.dist-info/METADATA
SnapHiC_D-0.1.0.dist-info/WHEEL
SnapHiC_D-0.1.0.dist-info/entry_points.txt
SnapHiC_D-0.1.0.dist-info/top_level.txt
SnapHiC_D-0.1.0.dist-info/RECORD
