Metadata-Version: 2.1
Name: SnapHiC-D
Version: 0.1.0
Summary: A computational pipeline to identify differential chromatin contacts from single cell Hi-C data
Home-page: https://github.com/lindsayhrlee/SnapHiC-D
Author: Lindsay Lee, Hongyu Yu
Author-email: hongyuyu@unc.edu
License: GNU
Requires-Python: >=3.6.8
License-File: LICENSE
Requires-Dist: click (>=7.1.2)
Requires-Dist: numpy (>=1.19.0)
Requires-Dist: pandas (>=1.1.5)
Requires-Dist: statsmodels (>=0.12.2)
Requires-Dist: qnorm (>=0.8.1)
Requires-Dist: scipy (>=1.5.4)
